README.md
setup.py
linkedin_auto_message_sender_bot/__init__.py
linkedin_auto_message_sender_bot.egg-info/PKG-INFO
linkedin_auto_message_sender_bot.egg-info/SOURCES.txt
linkedin_auto_message_sender_bot.egg-info/dependency_links.txt
linkedin_auto_message_sender_bot.egg-info/requires.txt
linkedin_auto_message_sender_bot.egg-info/top_level.txt