Metadata-Version: 2.1
Name: linkedin-auto-message-sender-bot
Version: 1.0.0
Summary: A python library to send messages to user on linkedin automatically.
Home-page: https://linkedin-api.datakund.com/en/latest/
Author: DataKund
Author-email: datakund@gmail.com
License: Apache License 2.0
Keywords: linkedin python bot_studio automation login send-messages messages
Platform: UNKNOWN
